[
    {
        "keyword": "COVID19",
        "age": {
            "10": 0.05,
            "20": 0.05,
            "30": 0.2,
            "40": 0.4,
            "50": 0.2,
            "60": 0.1
        },
        "gender": {
            "male": 0.7,
            "female": 0.3
        },
        "sentiment": {
            "positive": 0.2,
            "negative": 0.8
        },
        "summary": "이번주 코로나19 확진자가 지난주에 비해 크게 증가하여 정부가 강력하고 효과적인 방역대책을 고심하고 있다.",
        "tag": [
            "꾸준한",
            "중년층",
            "자투리시간",
            "비판적"
        ]
    },
    {
        "keyword": "대통령",
        "age": {
            "10": 0.01,
            "20": 0.04,
            "30": 0.1,
            "40": 0.2,
            "50": 0.3,
            "60": 0.35
        },
        "gender": {
            "male": 0.6,
            "female": 0.4
        },
        "sentiment": {
            "positive": 0.4,
            "negative": 0.6
        },
        "summary": "문재인 대통령이 미국을 방문했고 한반도 평화 정책 추진과 관련해 국제사회의 관심을 촉구했다.",
        "tag": [
            "꾸준한",
            "장년층",
            "출퇴근시간",
            "논쟁적"
        ]
    },
    {
        "keyword": "민노총",
        "age": {
            "10": 0.01,
            "20": 0.01,
            "30": 0.5,
            "40": 0.23,
            "50": 0.15,
            "60": 0.1
        },
        "gender": {
            "male": 0.7,
            "female": 0.3
        },
        "sentiment": {
            "positive": 0.1,
            "negative": 0.9
        },
        "summary": "불법집회 주도 혐의로 구속기소된 양경수 민주노총 위원장의 첫 재판이 30일 열린다.",
        "tag": [
            "뜨거운감자",
            "장년층",
            "자투리시간"
        ]
    },
    {
        "keyword": "특검",
        "age": {
            "10": 0.01,
            "20": 0.01,
            "30": 0.01,
            "40": 0.47,
            "50": 0.4,
            "60": 0.1
        },
        "gender": {
            "male": 0.8,
            "female": 0.2
        },
        "sentiment": {
            "positive": 0.1,
            "negative": 0.9
        },
        "summary": "화천대유 특검과 관련해 여, 야당이 첨예하게 대립하고 있다.",
        "tag": [
            "뜨거운감자",
            "40대",
            "일상시간"
        ]
    }
]